Workbook

Sheet 01. Branding_ReBranding
B2: Branding & Re-Branding — Designer Rates
B4: Service Category | C4: Sub-Service | D4: Scope / Deliverables | E4: Designer Rate
B5: Branding & Re-Branding | C5: Logo — Basic | D5: Basic logo concept, clean vector-ready design, standard file handoff | E5: =Sheet1!D8 -> 3000
B6: Branding & Re-Branding | C6: Logo — Professional | D6: Professional logo concepts, refinements, brand-ready file package | E6: =Sheet1!D9 -> 15000
B7: Branding & Re-Branding | C7: Brand Identity — Basic | D7: Basic visual identity system with logo usage, colors, and typography guidance | E7: =Sheet1!D10 -> 12500
B8: Branding & Re-Branding | C8: Brand Identity — Professional | D8: Professional brand identity system with expanded visual guidelines and assets | E8: =Sheet1!D11 -> 40000
B9: Branding & Re-Branding | C9: Rebranding Identity — Basic | D9: Basic rebranding identity refresh with updated visual direction and core assets | E9: =Sheet1!D12 -> 12500
B10: Branding & Re-Branding | C10: Rebranding Identity — Professional | D10: Professional rebranding package with full identity refresh and brand guidelines | E10: =Sheet1!D13 -> 40000

Sheet 02. Marketing_Materials
B2: Marketing Materials — Designer Rates
B4: Main Category | C4: Digital / Print | D4: Sub-Service | E4: Sub-Sub Service | F4: Designer Rate | G4: Time Period
B5: Marketing Materials | C5: Digital | D5: Social Media Design | E5: Single Social Media Poster | F5: ₹400 – ₹800 | G5: 1 working day
B6: Marketing Materials | C6: Digital | D6: Social Media Design | E6: Premium Social Media Poster | F6: ₹1,000 – ₹2,500 | G6: 1 – 2 working days
B7: Marketing Materials | C7: Digital | D7: Social Media Design | E7: Festival / Greeting Poster | F7: ₹400 – ₹800 | G7: 1 working day
B8: Marketing Materials | C8: Digital | D8: Social Media Design | E8: Offer / Sale Poster | F8: ₹400 – ₹800 | G8: 1 working day
B9: Marketing Materials | C9: Digital | D9: Social Media Design | E9: Product / Service Poster | F9: ₹400 – ₹800 | G9: 1 working day
B10: Marketing Materials | C10: Digital | D10: Social Media Design | E10: Carousel Post — 3 Slides | F10: ₹1,500 – ₹2,500 | G10: 2 working days
B11: Marketing Materials | C11: Digital | D11: Social Media Design | E11: Carousel Post — 5 Slides | F11: ₹2,500 – ₹4,000 | G11: 2 – 3 working days
B12: Marketing Materials | C12: Digital | D12: Social Media Design | E12: Instagram / Facebook Story Creative | F12: ₹300 – ₹700 | G12: 1 working day
B13: Marketing Materials | C13: Digital | D13: Social Media Design | E13: WhatsApp Status Creative | F13: ₹300 – ₹700 | G13: 1 working day
B14: Marketing Materials | C14: Digital | D14: Video Support Design | E14: Reel Thumbnail | F14: ₹300 – ₹700 | G14: 1 working day
B15: Marketing Materials | C15: Digital | D15: Video Support Design | E15: YouTube Thumbnail | F15: ₹500 – ₹1,000 | G15: 1 working day
... B54: Marketing Materials | C54: Digital / Print | D54: Add-On | E54: Premium Stock Image / Paid Asset Use | F54: At actual cost + handling | G54: Based on availability

Sheet Add_Ons
B2: Add-ons — Designer Rates
B4: Service Category | C4: Sub-Service | D4: Scope / Deliverables | E4: Designer Rate
B5: Add-on | C5: Additional Size Adaptation | D5: Same design resized for another platform/format | E5: 300
B6: Add-on | C6: Extra Minor Revision | D6: Small text/colour/alignment correction after included revision | E6: 300
B7: Add-on | C7: Additional Language Version | D7: Same design adapted to another language | E7: 500
B8: Add-on | C8: Urgent Delivery | D8: Priority delivery depending on scope | E8: 1000
B9: Add-on | C9: Editable Source File Handover | D9: Source file handover, if agreed | E9: Custom

Sheet Sheet1
B5: Branding & Rebranding Rate Card | L5: Color Legend
B6: Assumptions | D6: Margin % | E6: 0.3 | G6: 0.4 | H6: 0.6 | L6: Logo Services | M6: Rows 8–9
B7: Service Category | C7: Sub-Service | D7: Designer Rate | E7: Velnex Margin 30% | F7: Client Rate | G7: Sales Commission 40% of Velnex Margin | H7: Sales Commission 60% of Velnex Margin | I7: Velnex Retained After 40% Commission | J7: Velnex Retained After 60% Commission | L7: Brand Identity | M7: Rows 10–11
B8: Branding & Re-Branding | C8: Logo — Basic | D8: 3000 | E8: =D8*$E$6 -> 900 | F8: =D8+E8 -> 3900 | G8: =E8*$G$6 -> 360 | H8: =E8*$H$6 -> 540 | I8: =E8-G8 -> 540 | J8: =E8-H8 -> 360 | L8: Rebranding | M8: Rows 12–13
B9: Branding & Re-Branding | C9: Logo — Professional | D9: 15000 | E9: =D9*$E$6 -> 4500 | F9: =D9+E9 -> 19500 | G9: =E9*$G$6 -> 1800 | H9: =E9*$H$6 -> 2700 | I9: =E9-G9 -> 2700 | J9: =E9-H9 -> 1800 | L9: Editable Inputs | M9: Rates / % cells
B10: Branding & Re-Branding | C10: Brand Identity — Basic | D10: 12500 | E10: =D10*$E$6 -> 3750 | F10: =D10+E10 -> 16250 | G10: =E10*$G$6 -> 1500 | H10: =E10*$H$6 -> 2250 | I10: =E10-G10 -> 2250 | J10: =E10-H10 -> 1500 | L10: Calculated Outputs | M10: Formulas
B11: Branding & Re-Branding | C11: Brand Identity — Professional | D11: 40000 | E11: =D11*$E$6 -> 12000 | F11: =D11+E11 -> 52000 | G11: =E11*$G$6 -> 4800 | H11: =E11*$H$6 -> 7200 | I11: =E11-G11 -> 7200 | J11: =E11-H11 -> 4800 | L11: Digital Marketing | M11: Rows 19–21
B12: Branding & Re-Branding | C12: Rebranding Identity — Basic | D12: 12500 | E12: =D12*$E$6 -> 3750 | F12: =D12+E12 -> 16250 | G12: =E12*$G$6 -> 1500 | H12: =E12*$H$6 -> 2250 | I12: =E12-G12 -> 2250 | J12: =E12-H12 -> 1500 | L12: Print Marketing | M12: Rows 22–24
B13: Branding & Re-Branding | C13: Rebranding Identity — Professional | D13: 40000 | E13: =D13*$E$6 -> 12000 | F13: =D13+E13 -> 52000 | G13: =E13*$G$6 -> 4800 | H13: =E13*$H$6 -> 7200 | I13: =E13-G13 -> 7200 | J13: =E13-H13 -> 4800
B16: Marketing Materials - Digital & Print Rate Card
B18: Service Category | C18: Sub-Service | D18: Designer Rate | E18: Velnex Margin 30% | F18: Client Rate | G18: Sales Commission 40% of Velnex Margin | H18: Sales Commission 60% of Velnex Margin | I18: Velnex Retained After 40% Commission | J18: Velnex Retained After 60% Commission
B19: Marketing Materials - Digital & Print | C19: Social Media Post Design | E19: =IF($D19="","",$D19*$E$6) | F19: =IF($D19="","",$D19+E19) | G19: =IF($D19="","",E19*$G$6) | H19: =IF($D19="","",E19*$H$6) | I19: =IF($D19="","",E19-G19) | J19: =IF($D19="","",E19-H19)
B20: Marketing Materials - Digital & Print | C20: Digital Ad Creative | E20: =IF($D20="","",$D20*$E$6) | F20: =IF($D20="","",$D20+E20) | G20: =IF($D20="","",E20*$G$6) | H20: =IF($D20="","",E20*$H$6) | I20: =IF($D20="","",E20-G20) | J20: =IF($D20="","",E20-H20)
B21: Marketing Materials - Digital & Print | C21: Emailer / Newsletter Design | E21: =IF($D21="","",$D21*$E$6) | F21: =IF($D21="","",$D21+E21) | G21: =IF($D21="","",E21*$G$6) | H21: =IF($D21="","",E21*$H$6) | I21: =IF($D21="","",E21-G21) | J21: =IF($D21="","",E21-H21)
B22: Marketing Materials - Digital & Print | C22: Flyer / Poster Design | E22: =IF($D22="","",$D22*$E$6) | F22: =IF($D22="","",$D22+E22) | G22: =IF($D22="","",E22*$G$6) | H22: =IF($D22="","",E22*$H$6) | I22: =IF($D22="","",E22-G22) | J22: =IF($D22="","",E22-H22)
B23: Marketing Materials - Digital & Print | C23: Brochure Design | E23: =IF($D23="","",$D23*$E$6) | F23: =IF($D23="","",$D23+E23) | G23: =IF($D23="","",E23*$G$6) | H23: =IF($D23="","",E23*$H$6) | I23: =IF($D23="","",E23-G23) | J23: =IF($D23="","",E23-H23)
B24: Marketing Materials - Digital & Print | C24: Business Card / Stationery Design | E24: =IF($D24="","",$D24*$E$6) | F24: =IF($D24="","",$D24+E24) | G24: =IF($D24="","",E24*$G$6) | H24: =IF($D24="","",E24*$H$6) | I24: =IF($D24="","",E24-G24) | J24: =IF($D24="","",E24-H24)

Sheet Invoice_Quotation
B2: VELNEX - QUOTATION / INVOICE
B4: From | C4: Velnex | E4: Document Type | F4: Quotation
B5: Address | E5: Document No.
B6: Email / Phone | C6: operations@velnex.in / +971 555936942 | E6: Date | F6: =TODAY() -> 46210
B7: GSTIN | E7: Valid Until | F7: =F6+15 -> 46225
B8: Prepared By | E8: Payment Terms | F8: 50% Advance / Balance on Delivery
E9: Currency | F9: INR
B10: Bill To
B11: Client Name
B12: Company
B13: Email / Phone
B14: Project / Brand
B16: # | C16: Service Category | D16: Sub-Service | E16: Qty | F16: Unit Rate | G16: Amount
B17: 1 | C17: =IFERROR(_xlfn.XLOOKUP(D17,Sheet1!$C$8:$C$13,Sheet1!$B$8:$B$13,""),"") | F17: =IFERROR(_xlfn.XLOOKUP(D17,Sheet1!$C$8:$C$13,Sheet1!$F$8:$F$13,""),"") | G17: =IFERROR(E17*F17,"")
B18: 2 | C18: =IFERROR(_xlfn.XLOOKUP(D18,Sheet1!$C$8:$C$13,Sheet1!$B$8:$B$13,""),"") | F18: =IFERROR(_xlfn.XLOOKUP(D18,Sheet1!$C$8:$C$13,Sheet1!$F$8:$F$13,""),"") | G18: =IFERROR(E18*F18,"")
B19: 3 | C19: =IFERROR(_xlfn.XLOOKUP(D19,Sheet1!$C$8:$C$13,Sheet1!$B$8:$B$13,""),"") | F19: =IFERROR(_xlfn.XLOOKUP(D19,Sheet1!$C$8:$C$13,Sheet1!$F$8:$F$13,""),"") | G19: =IFERROR(E19*F19,"")
B20: 4 | C20: =IFERROR(_xlfn.XLOOKUP(D20,Sheet1!$C$8:$C$13,Sheet1!$B$8:$B$13,""),"") | F20: =IFERROR(_xlfn.XLOOKUP(D20,Sheet1!$C$8:$C$13,Sheet1!$F$8:$F$13,""),"") | G20: =IFERROR(E20*F20,"")
B21: 5 | C21: =IFERROR(_xlfn.XLOOKUP(D21,Sheet1!$C$8:$C$13,Sheet1!$B$8:$B$13,""),"") | F21: =IFERROR(_xlfn.XLOOKUP(D21,Sheet1!$C$8:$C$13,Sheet1!$F$8:$F$13,""),"") | G21: =IFERROR(E21*F21,"")
B22: 6 | C22: =IFERROR(_xlfn.XLOOKUP(D22,Sheet1!$C$8:$C$13,Sheet1!$B$8:$B$13,""),"") | F22: =IFERROR(_xlfn.XLOOKUP(D22,Sheet1!$C$8:$C$13,Sheet1!$F$8:$F$13,""),"") | G22: =IFERROR(E22*F22,"")
B23: 7 | C23: =IFERROR(_xlfn.XLOOKUP(D23,Sheet1!$C$8:$C$13,Sheet1!$B$8:$B$13,""),"") | F23: =IFERROR(_xlfn.XLOOKUP(D23,Sheet1!$C$8:$C$13,Sheet1!$F$8:$F$13,""),"") | G23: =IFERROR(E23*F23,"")
B24: 8 | C24: =IFERROR(_xlfn.XLOOKUP(D24,Sheet1!$C$8:$C$13,Sheet1!$B$8:$B$13,""),"") | F24: =IFERROR(_xlfn.XLOOKUP(D24,Sheet1!$C$8:$C$13,Sheet1!$F$8:$F$13,""),"") | G24: =IFERROR(E24*F24,"")
B25: 9 | C25: =IFERROR(_xlfn.XLOOKUP(D25,Sheet1!$C$8:$C$13,Sheet1!$B$8:$B$13,""),"") | F25: =IFERROR(_xlfn.XLOOKUP(D25,Sheet1!$C$8:$C$13,Sheet1!$F$8:$F$13,""),"") | G25: =IFERROR(E25*F25,"")
B26: 10 | C26: =IFERROR(_xlfn.XLOOKUP(D26,Sheet1!$C$8:$C$13,Sheet1!$B$8:$B$13,""),"") | F26: =IFERROR(_xlfn.XLOOKUP(D26,Sheet1!$C$8:$C$13,Sheet1!$F$8:$F$13,""),"") | G26: =IFERROR(E26*F26,"")
B28: Notes | F28: Subtotal | G28: =SUM(G17:G26) -> 0
B29: 1. Unit rates auto-fill from the Rate Card when Sub-Service is entered. | F29: Discount % | G29: 0
B30: 2. Final scope, timelines, and deliverables should be confirmed before kickoff. | F30: Discount Amount | G30: =G28*G29 -> 0
B31: 3. Taxes and discounts can be edited in the summary section. | F31: GST % | G31: 0.18
F32: GST Amount | G32: =(G28-G30)*G31 -> 0
B33: Terms & Conditions | F33: Grand Total | G33: =G28-G30+G32 -> 0
B34: • Quotation validity follows the Valid Until date above. | F34: Amount Received | G34: 0
B35: • Work begins after advance payment and confirmation of scope. | F35: Balance Due | G35: =G33-G34 -> 0
B36: • Additional revisions or scope changes may be billed separately.
B37: • Final files are released after full payment clearance.
B40: Thank you for your business!
